MALDIpy/__init__.py
MALDIpy/featureplot.py
MALDIpy/msi_data.py
MALDIpy/multi_sample.py
MALDIpy/projection.py
MALDIpy/single_cell.py
MALDIpy/shell/__init__.py
MALDIpy/shell/msi_data.py
MALDIpy/shell/usage.py
MALDIpy/src/temp.txt
MALDIpy-0.1.5.dist-info/LICENSE
MALDIpy-0.1.5.dist-info/METADATA
MALDIpy-0.1.5.dist-info/WHEEL
MALDIpy-0.1.5.dist-info/entry_points.txt
MALDIpy-0.1.5.dist-info/top_level.txt
MALDIpy-0.1.5.dist-info/zip-safe
MALDIpy-0.1.5.dist-info/RECORD
