Metadata-Version: 2.1
Name: MALDIpy
Version: 0.1.5
Summary: MALDI-MS data analysis at the single-cell level (Tutorials available at https://github.com/TheHumphreysLab/MALDIpy
Home-page: https://github.com/TheHumphreysLab
Author: Haikuo Li; Qiao Xuanyuan; Dian Li; Benjamin Humphreys
Author-email: haikuolibio@gmail.com
License: UNKNOWN
Platform: UNKNOWN
Classifier: Programming Language :: Python :: 3
Requires-Python: >=3.6
